yaml2bib/__init__.py
yaml2bib/_version.py
yaml2bib/_yaml2bib.py
yaml2bib-0.2.0.dist-info/LICENSE
yaml2bib-0.2.0.dist-info/METADATA
yaml2bib-0.2.0.dist-info/WHEEL
yaml2bib-0.2.0.dist-info/entry_points.txt
yaml2bib-0.2.0.dist-info/top_level.txt
yaml2bib-0.2.0.dist-info/RECORD
