Metadata-Version: 2.1
Name: yaml2bib
Version: 0.2.0
Summary: Convert a yaml file containing (key -> DOI) pairs to bib file with the correct journal abbreviations.
Maintainer-email: Bas Nijholt <bas@nijho.lt>
License: MIT
Project-URL: homepage, https://yaml2bib.readthedocs.io/en/latest/
Project-URL: documentation, https://yaml2bib.readthedocs.io/
Project-URL: repository, https://github.com/basnijholt/yaml2bib
Classifier: Intended Audience :: Science/Research
Classifier: Operating System :: OS Independent
Classifier: Programming Language :: Python
Classifier: Programming Language :: Python :: 3
Classifier: Topic :: Scientific/Engineering
Classifier: Topic :: Utilities
Classifier: License :: OSI Approved :: MIT License
Classifier: Programming Language :: Python :: 3.8
Classifier: Programming Language :: Python :: 3.9
Classifier: Programming Language :: Python :: 3.10
Classifier: Programming Language :: Python :: 3.11
Requires-Python: >=3.8
License-File: LICENSE
Requires-Dist: Click
Requires-Dist: crossrefapi
Requires-Dist: diskcache
Requires-Dist: requests
Requires-Dist: pylatexenc
Requires-Dist: pyyaml
Requires-Dist: tqdm
Requires-Dist: versioningit
Provides-Extra: test
Requires-Dist: pytest; extra == "test"
Requires-Dist: pytest-cov; extra == "test"
Requires-Dist: tox; extra == "test"
Provides-Extra: dev
Requires-Dist: pre-commit; extra == "dev"
Provides-Extra: docs
Requires-Dist: sphinx; extra == "docs"
Requires-Dist: sphinx-rtd-theme; extra == "docs"
Requires-Dist: myst-parser; extra == "docs"
Requires-Dist: sphinxcontrib.apidoc; extra == "docs"
